gdmec23120143/__init__.py
gdmec23120143-0.1.1.dist-info/METADATA
gdmec23120143-0.1.1.dist-info/WHEEL
gdmec23120143-0.1.1.dist-info/entry_points.txt
gdmec23120143-0.1.1.dist-info/RECORD
